nzxvirtualtrader/__init__.py
nzxvirtualtrader/start.py
nzx_virtual_trading-0.0.1.dist-info/METADATA
nzx_virtual_trading-0.0.1.dist-info/WHEEL
nzx_virtual_trading-0.0.1.dist-info/top_level.txt
nzx_virtual_trading-0.0.1.dist-info/RECORD
